dymmond_settings/__init__.py
dymmond_settings/base.py
dymmond_settings/conf.py
dymmond_settings/enums.py
dymmond_settings/exceptions.py
dymmond_settings/functional.py
dymmond_settings/module_loading.py
dymmond_settings/py.typed
dymmond_settings-1.0.4.dist-info/METADATA
dymmond_settings-1.0.4.dist-info/WHEEL
dymmond_settings-1.0.4.dist-info/licenses/LICENSE
dymmond_settings-1.0.4.dist-info/RECORD
